libre_finance/__init__.py
libre_finance/app.py
libre_finance/constants.py
libre_finance/database/__init__.py
libre_finance/database/mariadb.py
libre_finance/database/spec.py
libre_finance-0.1.0.dist-info/LICENSE
libre_finance-0.1.0.dist-info/METADATA
libre_finance-0.1.0.dist-info/WHEEL
libre_finance-0.1.0.dist-info/top_level.txt
libre_finance-0.1.0.dist-info/RECORD
