Metadata-Version: 2.2
Name: libre-finance
Version: 0.1.0
Summary: This tool helps financial consumers freely utilize financial services by interest calculating.
Author-email: minwook-shin <minwook0106@gmail.com>
Project-URL: Homepage, https://github.com/minwook-shin/libre-finance
Project-URL: Bug Tracker, https://github.com/minwook-shin/libre-finance/issues
Classifier: Programming Language :: Python :: 3
Classifier: License :: OSI Approved :: MIT License
Classifier: Operating System :: OS Independent
Requires-Python: >=3.10
License-File: LICENSE
Provides-Extra: dev
Requires-Dist: pytest; extra == "dev"
Requires-Dist: build; extra == "dev"
Requires-Dist: twine; extra == "dev"
Provides-Extra: sql
Requires-Dist: PyMySQL==1.1.1; extra == "sql"
Requires-Dist: SQLAlchemy==2.0.37; extra == "sql"
